keyforge.py
keyforge-0.1.0.dist-info/METADATA
keyforge-0.1.0.dist-info/WHEEL
keyforge-0.1.0.dist-info/entry_points.txt
keyforge-0.1.0.dist-info/top_level.txt
keyforge-0.1.0.dist-info/RECORD
