Metadata-Version: 2.4
Name: keyforge
Version: 0.1.0
Summary: Test API keys for multiple LLM providers
Requires-Python: >=3.8
Requires-Dist: requests>=2.25.0
Requires-Dist: python-dotenv>=0.19.0
